Pystyiles/__init__.py
Pystyiles/colors.py
Pystyiles-0.9.dist-info/METADATA
Pystyiles-0.9.dist-info/WHEEL
Pystyiles-0.9.dist-info/top_level.txt
Pystyiles-0.9.dist-info/RECORD
